[{"categories":null,"contents":"I\u0026rsquo;m an UX Web Designer \u0026amp; Front-End Developer based in Barcelona now working in Corporació Catalana de Mitjans Audiovisuals. I like to build clean, appealing, and functional interfaces which comply with the latest standards. Web and mobile designing is my passion, I like to learn new things and always explore about latest trends and happenings all around. Passionate of Agile Methodologies / SCRUM.\nSkills: Expert Knowledge of W3C standards and Semantic Markup, CSS3, SEO, Cross Browser Compatibility, Javascript, Usability, Bootstrap, LESS, SASS, SVN, Git, Responsive web Design, Accessibility Guidelines, Content Management System and PHP / MySQL.\nI have two children. I like challenges and run long distance races, cycling and paragliding. Padel addict.\n","permalink":"https://www.ferranmoron.com/en/about/","tags":null,"title":"About me"}]